trytond/modules/health_calendar/COPYING
trytond/modules/health_calendar/README.rst
trytond/modules/health_calendar/__init__.py
trytond/modules/health_calendar/data/messages/messages.xml
trytond/modules/health_calendar/exceptions.py
trytond/modules/health_calendar/health_calendar.py
trytond/modules/health_calendar/health_calendar_view.xml
trytond/modules/health_calendar/icons/calendar_icon.svg
trytond/modules/health_calendar/icons/execute_icon.svg
trytond/modules/health_calendar/locale/ar.po
trytond/modules/health_calendar/locale/de.po
trytond/modules/health_calendar/locale/el.po
trytond/modules/health_calendar/locale/eo.po
trytond/modules/health_calendar/locale/es.po
trytond/modules/health_calendar/locale/fr.po
trytond/modules/health_calendar/locale/health_calendar.pot
trytond/modules/health_calendar/locale/it_IT.po
trytond/modules/health_calendar/locale/ja_JP.po
trytond/modules/health_calendar/locale/ka.po
trytond/modules/health_calendar/locale/lo.po
trytond/modules/health_calendar/locale/pt_BR.po
trytond/modules/health_calendar/locale/sv.po
trytond/modules/health_calendar/locale/tr.po
trytond/modules/health_calendar/locale/uk.po
trytond/modules/health_calendar/locale/zh_CN.po
trytond/modules/health_calendar/pyproject.toml
trytond/modules/health_calendar/tests/__init__.py
trytond/modules/health_calendar/tests/test_health_calendar.py
trytond/modules/health_calendar/tryton.cfg
trytond/modules/health_calendar/view/gnuhealth_appointment_calendar.xml
trytond/modules/health_calendar/view/gnuhealth_calendar_appointment.xml
trytond/modules/health_calendar/view/gnuhealth_calendar_user.xml
trytond/modules/health_calendar/view/gnuhealth_create_appointment_start_form.xml
trytond/modules/health_calendar/wizard/__init__.py
trytond/modules/health_calendar/wizard/health_calendar_wizard.xml
trytond/modules/health_calendar/wizard/wizard_health_calendar.py
gnuhealth_calendar-5.0.3.dist-info/METADATA
gnuhealth_calendar-5.0.3.dist-info/WHEEL
gnuhealth_calendar-5.0.3.dist-info/licenses/COPYING
gnuhealth_calendar-5.0.3.dist-info/RECORD
